venvcleaner/__init__.py
venvcleaner/__main__.py
venvcleaner/main.py
venvcleaner-0.1.6.dist-info/METADATA
venvcleaner-0.1.6.dist-info/WHEEL
venvcleaner-0.1.6.dist-info/entry_points.txt
venvcleaner-0.1.6.dist-info/licenses/LICENSE
venvcleaner-0.1.6.dist-info/RECORD
