Metadata-Version: 2.4
Name: venvcleaner
Version: 0.1.6
Summary: A GUI tool for cleaning up Python virtual environments (venv directories).
License-Expression: MIT
License-File: LICENSE
Author: yamakox
Author-email: notolog.tech@gmail.com
Requires-Python: >=3.10
Classifier: Programming Language :: Python :: 3
Classifier: License :: OSI Approved :: MIT License
Classifier: Operating System :: OS Independent
Classifier: Development Status :: 4 - Beta
Requires-Dist: click (>=8.3.0)
Requires-Dist: wxpython (>=4.2.1)
Project-URL: Homepage, https://github.com/yamakox/VenvCleaner
Project-URL: Issues, https://github.com/yamakox/VenvCleaner/issues
Project-URL: Repository, https://github.com/yamakox/VenvCleaner.git
